README.md
setup.py
kgtools/__init__.py
kgtools/annotation.py
kgtools/func.py
kgtools/htmlparser.py
kgtools/preprocessing.py
kgtools/saver.py
kgtools/spider.py
kgtools/symbol.py
kgtools/tokenizer.py
kgtools/w2v.py
kgtools/wrapper.py
kgtools.egg-info/PKG-INFO
kgtools.egg-info/SOURCES.txt
kgtools.egg-info/dependency_links.txt
kgtools.egg-info/not-zip-safe
kgtools.egg-info/requires.txt
kgtools.egg-info/top_level.txt
kgtools/nlp/__init__.py
kgtools/nlp/tokenizer.py
kgtools/type/__init__.py
kgtools/type/sentence.py
kgtools/type/span.py
kgtools/type/token.py
kgtools/type/type.py
kgtools/type/vocab.py
test/test.py
test/test2.py
test/test3.py
test/test_tokenizer.py